{"meshTagsMajor":["Incidental Findings","Coronary Angiography"],"keywords":["Aged","aortic valve/anomalies","coronary angiography","heart defects, congenital/diagnosis","heart valve diseases"],"meshTags":["Angina Pectoris","Female","Cardiovascular Agents","Incidental Findings","Humans","Coronary Angiography","Aged","Coronary Stenosis","Aortic Valve"],"meshMinor":["Angina Pectoris","Female","Cardiovascular Agents","Humans","Aged","Coronary Stenosis","Aortic Valve"],"organisms":["9606","9606"],"publicationTypes":["Case Reports","Journal Article"],"abstract":"We report the case of a 75-year-old woman who presented with stable angina and with a quadricuspid aortic valve, which consisted of 4 equal-sized leaflets that were diagnosed incidentally upon coronary angiography. Despite the patient\u0027s advanced age, the abnormal valve was functioning almost normally.","title":"Quadricuspid aortic valve without severe dysfunction despite advanced age.","pubmedId":"19876437"}