{"meshTags":["Prostate-Specific Antigen","Prostate","Prostatic Neoplasms","Humans","Kallikreins","Male","Early Detection of Cancer"],"meshMinor":["Prostate-Specific Antigen","Prostate","Prostatic Neoplasms","Humans","Kallikreins","Male","Early Detection of Cancer"],"publicationTypes":["Comment","Editorial"],"title":"Unorganized prostate-specific antigen-based screening for prostate cancer: more harm than benefit. When will we finally start to implement guidelines and risk assessment tools in clinical practice?","pubmedId":"25769985"}